pyee/__init__.py
pyee/asyncio.py
pyee/base.py
pyee/cls.py
pyee/executor.py
pyee/py.typed
pyee/trio.py
pyee/twisted.py
pyee/uplift.py
pyee-12.1.1.dist-info/LICENSE
pyee-12.1.1.dist-info/METADATA
pyee-12.1.1.dist-info/WHEEL
pyee-12.1.1.dist-info/top_level.txt
pyee-12.1.1.dist-info/RECORD
